pyvss/__init__.py
pyvss/const.py
pyvss/enums.py
pyvss/exceptions.py
pyvss/helper.py
pyvss/manager.py
pyvss-2025.2.1.dist-info/LICENSE
pyvss-2025.2.1.dist-info/METADATA
pyvss-2025.2.1.dist-info/WHEEL
pyvss-2025.2.1.dist-info/top_level.txt
pyvss-2025.2.1.dist-info/RECORD
