Metadata-Version: 2.1
Name: pyvss
Version: 2025.2.1
Summary: ITS Private Cloud Python Client
Home-page: https://gitlab-ee.eis.utoronto.ca/vss/py-vss
Download-URL: https://gitlab-ee.eis.utoronto.ca/vss/py-vss/archive/2025.2.1.zip
Author: University of Toronto
Author-email: vss-apps@eis.utoronto.ca
Maintainer-email: vss-py@eis.utoronto.ca
License: MIT
Project-URL: Bug Reports, https://gitlab-ee.eis.utoronto.ca/vss/py-vss/issues
Project-URL: Documentation, https://eis.utorotno.ca/~vss/py-vss/
Project-URL: Source, https://gitlab-ee.eis.utoronto.ca/vss/py-vss
Platform: any
Classifier: Development Status :: 5 - Production/Stable
Classifier: Intended Audience :: System Administrators
Classifier: Intended Audience :: End Users/Desktop
Classifier: Intended Audience :: Developers
Classifier: License :: OSI Approved :: MIT License
Classifier: Operating System :: OS Independent
Classifier: Programming Language :: Python :: 3.8
Classifier: Programming Language :: Python :: 3.9
Classifier: Programming Language :: Python :: 3.10
Classifier: Topic :: Software Development :: Libraries :: Python Modules
Classifier: Topic :: System :: Systems Administration
Requires-Python: >=3.7.5
License-File: LICENSE
Requires-Dist: requests >=2.32.3
Requires-Dist: pyjwt >=2.6.0
Provides-Extra: dev
Requires-Dist: flake8 ==6.0.0 ; extra == 'dev'
Requires-Dist: nose ==1.3.7 ; extra == 'dev'
Requires-Dist: coverage ==6.5.0 ; extra == 'dev'
Requires-Dist: pytz ==2022.6 ; extra == 'dev'
Requires-Dist: wheel ==0.38.4 ; extra == 'dev'
Requires-Dist: minio ==7.2.15 ; extra == 'dev'
Requires-Dist: sphinx-rtd-theme ==1.3.0 ; extra == 'dev'
Requires-Dist: Sphinx ==7.2.6 ; extra == 'dev'
Requires-Dist: bump2version ==1.0.1 ; extra == 'dev'
Requires-Dist: sphinxcontrib-jquery ==4.1 ; extra == 'dev'
Requires-Dist: sphinxcontrib-confluencebuilder ==2.11.0 ; extra == 'dev'
Provides-Extra: stor
Requires-Dist: minio ==7.2.15 ; extra == 'stor'
Provides-Extra: test
Requires-Dist: flake8 ==6.0.0 ; extra == 'test'
Requires-Dist: nose ==1.3.7 ; extra == 'test'
Requires-Dist: coverage ==6.5.0 ; extra == 'test'
Requires-Dist: pytz ==2022.6 ; extra == 'test'
Requires-Dist: wheel ==0.38.4 ; extra == 'test'
Requires-Dist: minio ==7.2.15 ; extra == 'test'
